bimage/__init__.py
bimage/__main__.py
bimage/downloader.py
bimage/handler.py
bimage/validator.py
bimage-0.1.0.dist-info/LICENSE
bimage-0.1.0.dist-info/METADATA
bimage-0.1.0.dist-info/WHEEL
bimage-0.1.0.dist-info/entry_points.txt
bimage-0.1.0.dist-info/top_level.txt
bimage-0.1.0.dist-info/RECORD
