Metadata-Version: 2.1
Name: bimage
Version: 0.1.0
Summary: A bulk image scraper for use in ML
Home-page: https://github.com/xobek/bimage
Author: xobek
Author-email: xobekme@gmail.com
License: MIT
Classifier: License :: OSI Approved :: MIT License
Classifier: Programming Language :: Python :: 3
Requires-Python: >=3.6
License-File: LICENSE
Requires-Dist: duckduckgo-search ==3.*
Requires-Dist: Pillow ==10.*
Requires-Dist: fastdownload ==0.0.*
